opener/__init__.py
opener/open_the_lock.py
opener-0.0.4.dist-info/LICENSE
opener-0.0.4.dist-info/METADATA
opener-0.0.4.dist-info/WHEEL
opener-0.0.4.dist-info/top_level.txt
opener-0.0.4.dist-info/RECORD
