Metadata-Version: 2.1
Name: opener
Version: 0.0.4
Summary: Solve open the lock puzzle.
Home-page: http://github.com/arsho/opener
Author: Ahmedur Rahman Shovon
Author-email: shovon.sylhet@gmail.com
License: MIT
Keywords: opener puzzle open_the_lock solver
Platform: UNKNOWN
Classifier: Operating System :: OS Independent
Classifier: License :: OSI Approved :: MIT License
Classifier: Environment :: Console
Classifier: Programming Language :: Python
Classifier: Programming Language :: Python :: 2
Classifier: Programming Language :: Python :: 3
Classifier: Development Status :: 5 - Production/Stable
Classifier: Topic :: Games/Entertainment :: Puzzle Games
Classifier: Topic :: Scientific/Engineering :: Mathematics
